tuzue/__init__.py
tuzue/binput.py
tuzue/inspector.py
tuzue/logger.py
tuzue/view.py
tuzue/ui/__init__.py
tuzue/ui/tcurses.py
tuzue-0.1.5.data/data/share/doc/python-tuzue/AUTHORS
tuzue-0.1.5.data/data/share/doc/python-tuzue/LICENSE
tuzue-0.1.5.data/data/share/doc/python-tuzue/README.md
tuzue-0.1.5.dist-info/LICENSE
tuzue-0.1.5.dist-info/METADATA
tuzue-0.1.5.dist-info/WHEEL
tuzue-0.1.5.dist-info/top_level.txt
tuzue-0.1.5.dist-info/RECORD
