Metadata-Version: 2.1
Name: tuzue
Version: 0.1.5
Summary: [archived] Fuzzy-filtering menu-based interactive curses interface for python, plus utilities
Home-page: http://github.com/lpenz/tuzue
Author: "Leandro Lisboa Penz"
Author-email: "lpenz@lpenz.org"
License: MIT
Classifier: Development Status :: 1 - Planning
Classifier: Environment :: Console
Classifier: License :: OSI Approved :: MIT License
Classifier: Operating System :: POSIX :: Linux
Classifier: Programming Language :: Python :: 2
Classifier: Programming Language :: Python :: 3
Requires-Python: >=3.6
License-File: LICENSE
Provides-Extra: test
Requires-Dist: pytest ; extra == 'test'
Requires-Dist: pytest-cov ; extra == 'test'
Requires-Dist: pyftpdlib ; extra == 'test'
